mat_llm_cli/__init__.py
mat_llm_cli/__version__.py
mat_llm_cli/cli.py
mat_llm_cli/utils.py
mat_llm_cli-0.1.0.dist-info/entry_points.txt
mat_llm_cli-0.1.0.dist-info/licenses/LICENSE
mat_llm_cli-0.1.0.dist-info/WHEEL
mat_llm_cli-0.1.0.dist-info/METADATA
mat_llm_cli-0.1.0.dist-info/RECORD
