Metadata-Version: 2.4
Name: mat_llm_cli
Version: 0.1.0
Summary: Contains useful CLI tools to leverage LLM APIs.
Author: Matthieu Dagommer
Requires-Python: ~=3.10.0
Classifier: Programming Language :: Python :: 3
Classifier: License :: OSI Approved :: MIT License
License-File: LICENSE
Requires-Dist: mkdocs
Requires-Dist: pip
Requires-Dist: pytest
Requires-Dist: python-dotenv
Requires-Dist: ruff
Requires-Dist: GitPython
Requires-Dist: openai
Requires-Dist: pyprojroot
Requires-Dist: typer
